LICENSE
README.md
setup.py
jenc/__init__.py
jenc/__main__.py
jenc/_version.py
jenc.egg-info/PKG-INFO
jenc.egg-info/SOURCES.txt
jenc.egg-info/dependency_links.txt
jenc.egg-info/requires.txt
jenc.egg-info/top_level.txt
jenc.egg-info/zip-safe