Metadata-Version: 2.1
Name: jenc
Version: 0.0.5
Summary: Python jenc jpencconverter encryption implementation
Home-page: https://github.com/clach04/jenc-py
Author: clach04
Maintainer: clach04
License: Apache Software License
Platform: any
Classifier: Development Status :: 4 - Beta
Classifier: License :: OSI Approved :: Apache Software License
Classifier: Intended Audience :: Developers
Classifier: Operating System :: OS Independent
Classifier: Operating System :: Microsoft :: Windows :: Windows NT/2000
Classifier: Operating System :: POSIX
Classifier: Operating System :: POSIX :: Linux
Classifier: Operating System :: Unix
Classifier: Programming Language :: Python
Classifier: Programming Language :: Python :: 2
Classifier: Programming Language :: Python :: 2.7
Classifier: Programming Language :: Python :: 3
Classifier: Programming Language :: Python :: 3.12
Classifier: Topic :: Security :: Cryptography
License-File: LICENSE
Requires-Dist: pycryptodome
